<?xml version="1.0" ?>
<shorthand>
  <name>waseda</name>
  <dictionary>
    <entry>
      <index>キョー</index>
      <characterNames>WasedaKyoh</characterNames>
    </entry>
  </dictionary>
  <characters>
    <character>
      <name>WasedaKyoh</name>
      <description>きょー</description>
      <model>SW4NE1SW3</model>
      <head>SW</head>
      <tail>SW</tail>
      <headModel>SW4</headModel>
      <tailModel>NE1</tailModel>
      <color>black</color>
      <bold>false</bold>
      <offsetX>1.4</offsetX>
      <offsetY>-3.1</offsetY>
      <right>0</right>
      <glyph>
        <key>X_X</key>
        <path> M 0.000000 0.000000 l -1.026070 2.819020 l 1.536570 -1.234200 l -1.026080 2.819030</path>
        <exitX>-0.51558</exitX>
        <exitY>4.40385</exitY>
        <length>7.971</length>
      </glyph>
    </character>
  </characters>
</shorthand>

